flashbots/__init__.py
flashbots/constants.py
flashbots/flashbots.py
flashbots/middleware.py
flashbots/provider.py
flashbots/types.py
flashbots-2.0.0.dist-info/LICENSE
flashbots-2.0.0.dist-info/METADATA
flashbots-2.0.0.dist-info/WHEEL
flashbots-2.0.0.dist-info/top_level.txt
flashbots-2.0.0.dist-info/RECORD
