Metadata-Version: 2.1
Name: flashbots
Version: 2.0.0
Summary: web3-flashbots.py
Home-page: https://github.com/flashbots/web3-flashbots
Author: Georgios Konstantopoulos
Author-email: me@gakonst.com
Maintainer: zeroXbrock
Maintainer-email: brock@flashbots.net
Requires-Python: >=3.9,<4.0
License-File: LICENSE
Requires-Dist: web3<7,>=6
